python_aternos/__init__.py
python_aternos/ataccount.py
python_aternos/atclient.py
python_aternos/atconf.py
python_aternos/atconnect.py
python_aternos/aterrors.py
python_aternos/atfile.py
python_aternos/atfm.py
python_aternos/atjsparse.py
python_aternos/atlog.py
python_aternos/atmd5.py
python_aternos/atplayers.py
python_aternos/atserver.py
python_aternos/atwss.py
py_aternos-3.0.74.dist-info/LICENSE
py_aternos-3.0.74.dist-info/METADATA
py_aternos-3.0.74.dist-info/NOTICE
py_aternos-3.0.74.dist-info/WHEEL
py_aternos-3.0.74.dist-info/top_level.txt
py_aternos-3.0.74.dist-info/RECORD
